{
    "lang": "en",
    "langName": "English",
    "title": "Snowpeak Blog",
    "description": "Sharing and discussing cutting-edge technologies such as AI, cloud computing, and GitHub Copilot",
    "keywords": "AI, GitHub Copilot, Azure Cloud, Cloud Computing, Front-end Technology, Back-end Technology, Web Development, Software Engineering",
    "read": "Read",
    "article": "Article",
    "summary": "Summary",
    "noResults": "No related articles found",
    "tryOtherKeywords": "Please try other keywords or view all articles",
    "ReadTry": "Read & Try",
    "searchPlaceholder": "Search article titles, content or tags...",
    "published": "Published",
    "reading_time": "Reading time",
    "category": "Category",
    "all": "All",
    "tags": "Tags",
    "home": "Home",
    "tool": "Tools",
    "about": "About",
    "wechat_account": "WeChat Account",
    "wechat_tech_warm": "Tech Warm Life",
    "quick_links": "Quick Links",
    "latest_articles": "Latest Articles",
    "demo_examples": "Demo Examples",
    "tech_stack": "Tech Stack",
    "responsive_design": "Responsive Design",
    "copyright_text": "Snowpeak Blog. Running on GitHub Pages.",
    "categoryMap": {
        "AI": "AI",
        "Azure": "Azure",
        "Development": "Development",
        "Tools": "Tools",
        "Cloud Computing": "Cloud Computing",
        "Backend": "Backend",
        "Database": "Database",
        "Frontend": "Frontend",
        "Web": "Web",
        "System": "System",
        "Network": "Network",
        "Mobile": "Mobile Development",
        "Software": "Software",
        "Programming": "Programming",
        "Framework": "Framework"
    }
}